odoo/addons/cooperator_api_logs/README.rst
odoo/addons/cooperator_api_logs/__init__.py
odoo/addons/cooperator_api_logs/__manifest__.py
odoo/addons/cooperator_api_logs/i18n/cooperator_api_logs.pot
odoo/addons/cooperator_api_logs/migrations/12.0.1.0.0/pre-migration.py
odoo/addons/cooperator_api_logs/models/__init__.py
odoo/addons/cooperator_api_logs/models/cooperator_api_log.py
odoo/addons/cooperator_api_logs/readme/CONTRIBUTORS.rst
odoo/addons/cooperator_api_logs/readme/DESCRIPTION.rst
odoo/addons/cooperator_api_logs/security/ir.model.access.csv
odoo/addons/cooperator_api_logs/static/description/index.html
odoo/addons/cooperator_api_logs/views/api_log_views.xml
odoo12_addon_cooperator_api_logs-12.0.1.0.0.99.dev4.dist-info/METADATA
odoo12_addon_cooperator_api_logs-12.0.1.0.0.99.dev4.dist-info/WHEEL
odoo12_addon_cooperator_api_logs-12.0.1.0.0.99.dev4.dist-info/top_level.txt
odoo12_addon_cooperator_api_logs-12.0.1.0.0.99.dev4.dist-info/RECORD
